tsdoc/__init__.py
tsdoc/py.typed
tsdoc/python/__init__.py
tsdoc/python/activity_header.py
tsdoc/python/activity_part.py
tsdoc/python/answer_abstract.py
tsdoc/python/answer_shape.py
tsdoc/python/comment_abstract.py
tsdoc/python/comment_concrete.py
tsdoc/python/comment_paragraph.py
tsdoc/python/comment_run_your_code.py
tsdoc/python/comment_section.py
tsdoc/python/comment_sentence.py
tsdoc/python/keywords.py
tsdoc/python/line_blank.py
tsdoc/python/model.py
tsdoc/python/point_tricky.py
tsdoc/python/positionable.py
tsdoc/python/question_abstract.py
tsdoc/python/question_review.py
tsdoc/python/question_shape.py
tsdoc/python/question_structure.py
tsdoc/python/representable.py
tsdoc/python/segment.py
tsdoc/python/solution_code.py
tsdoc/python/solution_item.py
tsdoc/python/solution_pseudocode.py
tsdoc/python/solution_shape.py
tsdoc/python/tsdoc.python.tx
tsdoc/python/vocabulary.py
tsdoc/python/vocabulary_term.py
tsdoc-0.1.1.dist-info/entry_points.txt
tsdoc-0.1.1.dist-info/LICENSE
tsdoc-0.1.1.dist-info/WHEEL
tsdoc-0.1.1.dist-info/METADATA
tsdoc-0.1.1.dist-info/RECORD
