Metadata-Version: 2.1
Name: tsdoc
Version: 0.1.1
Summary: TSDoc is an embedded comment language for TechSmart code files.
License: CC-BY-NC-ND-4.0
Author: Ryan Sobol
Author-email: ryan.sobol@techsmart.codes
Requires-Python: >=3.8,<4.0
Classifier: License :: Other/Proprietary License
Classifier: Programming Language :: Python :: 3
Classifier: Programming Language :: Python :: 3.8
Requires-Dist: attrs (>=19.3.0,<20.0.0)
Requires-Dist: textx_ls_core (>=0.1.1,<0.2.0)
